glpi_api.py
glpi_api-0.7.0.dist-info/LICENSE
glpi_api-0.7.0.dist-info/METADATA
glpi_api-0.7.0.dist-info/WHEEL
glpi_api-0.7.0.dist-info/top_level.txt
glpi_api-0.7.0.dist-info/RECORD
